redpie/__init__.py
redpie/redpie.py
redpie-0.0.1.dist-info/entry_points.txt
redpie-0.0.1.dist-info/WHEEL
redpie-0.0.1.dist-info/METADATA
redpie-0.0.1.dist-info/RECORD
