Metadata-Version: 2.1
Name: redpie
Version: 0.0.1
Summary: This modules allows you to use redis just like a Python dictionary
Home-page: https://github.com/victor141516/Redpie
License: UNKNOWN
Author: victor141516
Author-email: yomellamovictor@gmail.com
Maintainer: victor141516
Maintainer-email: yomellamovictor@gmail.com
Requires-Python: >=3.6
Classifier: Programming Language :: Python :: 3.6
Classifier: Intended Audience :: Developers
Classifier: License :: OSI Approved :: MIT License
Classifier: Topic :: Documentation
Classifier: Topic :: Software Development :: Documentation
Classifier: Topic :: Software Development :: Quality Assurance
Requires-Dist: redis
